Metadata-Version: 2.4
Name: Orange3-SingleCell
Version: 1.7.3
Summary: Add-on for bioinformatics analysis of single cell data.
Home-page: https://github.com/biolab/orange3-single-cell
Author: Bioinformatics Laboratory, FRI UL
Author-email: info@biolab.si
License: GPLv3+
Project-URL: Bug Tracker, https://github.com/biolab/orange3-single-cell/issues
Project-URL: Documentation, https://singlecell.biolab.si/docs/
Project-URL: Source Code, https://github.com/biolab/orange3-single-cell
Keywords: orange3 add-on
Requires-Python: >=3.6
License-File: LICENSE
Requires-Dist: Orange3>=3.34.0
Requires-Dist: orange3-bioinformatics>=4.0.0
Requires-Dist: fastdtw==0.3.2
Requires-Dist: pandas>=0.23
Requires-Dist: loompy>=2.0.10
Requires-Dist: xlrd>=2.0.1
Requires-Dist: openpyxl
Requires-Dist: anndata>=0.6.21
Requires-Dist: numpy
Requires-Dist: scikit-learn
Provides-Extra: doc
Requires-Dist: sphinx; extra == "doc"
Requires-Dist: recommonmark; extra == "doc"
Requires-Dist: sphinx_rtd_theme; extra == "doc"
Requires-Dist: docutils; extra == "doc"
Provides-Extra: package
Requires-Dist: twine; extra == "package"
Requires-Dist: wheel; extra == "package"
Provides-Extra: test
Requires-Dist: coverage; extra == "test"
Dynamic: license-file
Dynamic: provides-extra
Dynamic: requires-dist
